dokkey.cp312-win_amd64.pyd
dokkey-1.2.2.dist-info/LICENSE
dokkey-1.2.2.dist-info/METADATA
dokkey-1.2.2.dist-info/WHEEL
dokkey-1.2.2.dist-info/top_level.txt
dokkey-1.2.2.dist-info/RECORD
